enterprise_faq_system-0.1.0.dist-info/licenses/LICENSE
faq_system/__init__.py
faq_system/core.py
enterprise_faq_system-0.1.0.dist-info/METADATA
enterprise_faq_system-0.1.0.dist-info/WHEEL
enterprise_faq_system-0.1.0.dist-info/top_level.txt
enterprise_faq_system-0.1.0.dist-info/RECORD
