Metadata-Version: 2.4
Name: enterprise-faq-system
Version: 0.1.0
Summary: AI-powered FAQ system with hybrid search capabilities
Author-email: jayaprakash-shanmugam <jayaprkash7@gmail.com>
License-Expression: MIT
Project-URL: Homepage, https://github.com/jayaprakash-shanmugam/faq-system
Project-URL: Issues, https://github.com/jayaprakash-shanmugam/faq-system/issues
Requires-Python: >=3.8
License-File: LICENSE
Requires-Dist: numpy>=1.21.0
Requires-Dist: sentence-transformers>=2.2.0
Requires-Dist: faiss-cpu>=1.7.0
Requires-Dist: scikit-learn>=1.0.0
Provides-Extra: dev
Requires-Dist: pytest>=6.0; extra == "dev"
Requires-Dist: black; extra == "dev"
Requires-Dist: flake8; extra == "dev"
Dynamic: license-file
